[{"contentId":"2381406","typeid":"25"},{"contentId":"2518765","typeid":"12"},{"contentId":"2402006","typeid":"25"},{"contentId":"2372021","typeid":"25"},{"contentId":"2044565","typeid":"25"},{"contentId":"2401954","typeid":"25"},{"contentId":"2402735","typeid":"25"},{"contentId":"2360786","typeid":"12"},{"contentId":"2531423","typeid":"38"},{"contentId":"2516988","typeid":"39"},{"contentId":"2577328","typeid":"32"},{"contentId":"2531429","typeid":"38"},{"contentId":"2579389","typeid":"32"},{"contentId":"1747824","typeid":"32"},{"contentId":"2598695","typeid":"39"},{"contentId":"2569811","typeid":"32"},{"contentId":"1268116","typeid":"32"},{"contentId":"1832039","typeid":"32"},{"contentId":"983886","typeid":"32"},{"contentId":"131110","typeid":"28"},{"contentId":"127480","typeid":"12"},{"contentId":"1433504","typeid":"38"},{"contentId":"1797757","typeid":"39"},{"contentId":"2465071","typeid":"32"},{"contentId":"126273","typeid":"12"},{"contentId":"2019720","typeid":"12"},{"contentId":"2574970","typeid":"32"},{"contentId":"2572443","typeid":"39"},{"contentId":"2571935","typeid":"32"},{"contentId":"984586","typeid":"38"},{"contentId":"1928589","typeid":"39"},{"contentId":"129854","typeid":"14"},{"contentId":"130402","typeid":"14"},{"contentId":"129194","typeid":"12"},{"contentId":"795034","typeid":"39"},{"contentId":"135666","typeid":"39"},{"contentId":"2389419","typeid":"12"},{"contentId":"1604693","typeid":"39"},{"contentId":"250577","typeid":"39"},{"contentId":"129156","typeid":"12"},{"contentId":"597467","typeid":"39"},{"contentId":"125462","typeid":"12"},{"contentId":"2361026","typeid":"25"},{"contentId":"732484","typeid":"38"},{"contentId":"798518","typeid":"39"},{"contentId":"134960","typeid":"39"},{"contentId":"131912","typeid":"28"},{"contentId":"127257","typeid":"12"},{"contentId":"2384364","typeid":"12"},{"contentId":"142785","typeid":"32"},{"contentId":"2509701","typeid":"15"},{"contentId":"132215","typeid":"38"},{"contentId":"2013680","typeid":"39"},{"contentId":"2507936","typeid":"39"},{"contentId":"1865597","typeid":"32"},{"contentId":"129898","typeid":"14"},{"contentId":"125658","typeid":"12"},{"contentId":"2608451","typeid":"32"},{"contentId":"2607436","typeid":"32"},{"contentId":"1553085","typeid":"12"},{"contentId":"1896032","typeid":"32"},{"contentId":"2571998","typeid":"32"},{"contentId":"2400332","typeid":"12"},{"contentId":"125463","typeid":"12"},{"contentId":"125593","typeid":"12"},{"contentId":"789501","typeid":"28"},{"contentId":"608471","typeid":"39"},{"contentId":"126905","typeid":"12"},{"contentId":"127508","typeid":"12"},{"contentId":"2614885","typeid":"15"},{"contentId":"582215","typeid":"32"},{"contentId":"127423","typeid":"12"},{"contentId":"2525533","typeid":"39"},{"contentId":"2014192","typeid":"12"},{"contentId":"1953272","typeid":"39"},{"contentId":"126289","typeid":"12"},{"contentId":"1625067","typeid":"12"},{"contentId":"2577474","typeid":"39"},{"contentId":"2577481","typeid":"39"},{"contentId":"135696","typeid":"39"},{"contentId":"2580070","typeid":"39"},{"contentId":"2575770","typeid":"39"},{"contentId":"1884191","typeid":"12"},{"contentId":"2572145","typeid":"39"},{"contentId":"728386","typeid":"39"},{"contentId":"2386828","typeid":"15"},{"contentId":"1884202","typeid":"12"},{"contentId":"128498","typeid":"12"},{"contentId":"1258353","typeid":"15"},{"contentId":"1052741","typeid":"39"},{"contentId":"1884505","typeid":"12"},{"contentId":"2573961","typeid":"39"},{"contentId":"1781984","typeid":"32"},{"contentId":"127268","typeid":"12"},{"contentId":"2428116","typeid":"39"},{"contentId":"600680","typeid":"39"},{"contentId":"811327","typeid":"39"},{"contentId":"602895","typeid":"39"},{"contentId":"143017","typeid":"32"},{"contentId":"2581438","typeid":"32"},{"contentId":"1953998","typeid":"39"},{"contentId":"578400","typeid":"12"},{"contentId":"129141","typeid":"12"},{"contentId":"2615324","typeid":"12"},{"contentId":"1885246","typeid":"25"},{"contentId":"1916695","typeid":"12"},{"contentId":"2403809","typeid":"12"},{"contentId":"294369","typeid":"12"}]